setup.py
ezsec_requests/__init__.py
ezsec_requests/ezsec_requests.py
ezsec_requests.egg-info/PKG-INFO
ezsec_requests.egg-info/SOURCES.txt
ezsec_requests.egg-info/dependency_links.txt
ezsec_requests.egg-info/top_level.txt